{"USD":"1193.60","JPY":"1049.36","EUR":"1353.54","GBP":"1617.33","CAD":"949.07","CHF":"1308.13","AUD":"856.95","NZD":"801.62","CNH":"188.04","HKD":"153.28","TWD":"43.08","MNT":"0.42","KZT":"2.74","THB":"36.21","SGD":"887.60","IDR":"8.33","MYR":"285.11","PHP":"23.26","VND":"5.27","BND":"887.60","INR":"16.04","PKR":"6.78","BDT":"13.88","MXN":"58.28","BRL":"218.90","ARS":"11.44","SEK":"129.86","DKK":"181.83","NOK":"134.09","RUB":"15.42","HUF":"3.78","PLN":"298.88","CZK":"55.49","SAR":"318.20","QAR":"325.85","ILS":"379.97","JOD":"1683.38","KWD":"3948.13","BHD":"3166.30","AED":"324.97","TRY":"88.68","ZAR":"79.04","EGP":"75.98"}
