{"USD":"1194.20","JPY":"1047.50","EUR":"1352.67","GBP":"1610.68","CAD":"945.30","CHF":"1306.56","AUD":"853.55","NZD":"800.35","CNH":"188.43","HKD":"153.37","TWD":"43.23","MNT":"0.42","KZT":"2.73","THB":"36.18","SGD":"887.45","IDR":"8.33","MYR":"285.08","PHP":"23.28","VND":"5.26","BND":"887.45","INR":"16.00","PKR":"6.77","BDT":"13.90","MXN":"58.04","BRL":"217.60","ARS":"11.43","SEK":"128.93","DKK":"181.72","NOK":"132.90","RUB":"15.18","HUF":"3.74","PLN":"296.28","CZK":"55.14","SAR":"318.36","QAR":"327.99","ILS":"377.66","JOD":"1684.34","KWD":"3949.47","BHD":"3167.89","AED":"325.14","TRY":"88.66","ZAR":"78.28","EGP":"76.02"}
