{"USD":"1202.40","JPY":"1039.82","EUR":"1365.69","GBP":"1633.94","CAD":"950.18","CHF":"1308.45","AUD":"863.02","NZD":"814.51","CNH":"188.18","HKD":"154.20","TWD":"43.54","MNT":"0.42","KZT":"2.76","THB":"35.73","SGD":"886.73","IDR":"8.37","MYR":"285.67","PHP":"23.43","VND":"5.30","BND":"886.73","INR":"16.19","PKR":"6.79","BDT":"13.99","MXN":"58.98","BRL":"213.42","ARS":"11.64","SEK":"132.83","DKK":"183.58","NOK":"136.11","RUB":"15.87","HUF":"3.81","PLN":"300.47","CZK":"55.91","SAR":"320.51","QAR":"328.26","ILS":"386.89","JOD":"1695.79","KWD":"3972.51","BHD":"3189.05","AED":"327.37","TRY":"86.67","ZAR":"77.08","EGP":"76.56"}
